{
  "佐藤史": [
    "9017",
    "0071",
    "0070",
    "9051",
    "9001",
    "9052"
  ],
  "石塚": [
    "9046"
  ],
  "木村茂": [
    "0490",
    "1048"
  ],
  "塩﨑": [
    "9035",
    "9007"
  ],
  "萩野": [
    "1007",
    "1079",
    "1051",
    "1078"
  ],
  "町田": [
    "0476"
  ],
  "福山": [
    "0002",
    "0003"
  ],
  "吉川": [
    "1031",
    "1024"
  ],
  "松鹿": [
    "9018"
  ],
  "山本聡": [
    "9023",
    "9051",
    "9001",
    "0103",
    "9052"
  ],
  "毛利": [
    "9015",
    "9013"
  ],
  "佐藤智": [
    "9014",
    "1079",
    "1014",
    "1078",
    "1109"
  ],
  "今井": [
    "1084",
    "1006"
  ],
  "有川": [
    "1084",
    "1051",
    "1030"
  ],
  "根本": [
    "1084"
  ],
  "吉岡": [
    "1084"
  ],
  "沼田": [
    "8095"
  ],
  "高橋一": [
    "1073"
  ],
  "河野": [
    "0474",
    "0566"
  ],
  "三浦": [
    "0071",
    "0070"
  ],
  "師玉真": [
    "0071",
    "0070",
    "0090"
  ],
  "多田": [
    "0071",
    "0070",
    "0101"
  ],
  "中畑": [
    "0071",
    "0070"
  ],
  "山田陽": [
    "0071",
    "0070"
  ],
  "山本崇": [
    "0071",
    "0070"
  ],
  "門田": [
    "9019",
    "9042",
    "9025",
    "9051",
    "9001",
    "9052"
  ],
  "熊谷": [
    "1002",
    "1079",
    "1078",
    "0792"
  ],
  "大場": [
    "1042",
    "1044"
  ],
  "川島": [
    "1026",
    "1023",
    "1051"
  ],
  "神谷": [
    "8279",
    "9001"
  ],
  "高橋明": [
    "0001"
  ],
  "木村南": [
    "1079",
    "1074",
    "1078"
  ],
  "小池": [
    "1079",
    "1078"
  ],
  "高石": [
    "1051"
  ],
  "中根": [
    "1051"
  ],
  "渡部": [
    "1051",
    "1004",
    "1003"
  ],
  "水野": [
    "1051"
  ],
  "林": [
    "1046",
    "1013",
    "1106",
    "1047",
    "1102"
  ],
  "M科全教員": [
    "1046",
    "1106",
    "1047"
  ],
  "宮城": [
    "0472"
  ],
  "土谷": [
    "8094"
  ],
  "師玉": [
    "0088"
  ],
  "金井": [
    "0820"
  ],
  "広井": [
    "0820"
  ],
  "若杉": [
    "0820"
  ],
  "中尾": [
    "0820"
  ],
  "大平": [
    "0568"
  ],
  "高嶋": [
    "0230",
    "0232"
  ],
  "勝浦": [
    "0230",
    "0232"
  ],
  "松本剛": [
    "0230",
    "0232"
  ],
  "小机": [
    "1057"
  ],
  "田辺": [
    "9025",
    "9051",
    "9001",
    "9052"
  ],
  "端山": [
    "9045"
  ],
  "大木": [
    "0520",
    "0505"
  ],
  "小田切": [
    "0029"
  ],
  "鈴木芳": [
    "8139"
  ],
  "木村": [
    "1009",
    "1008"
  ],
  "小林": [
    "0004"
  ],
  "山本明": [
    "9024"
  ],
  "山本": [
    "8275"
  ],
  "照井": [
    "1089"
  ],
  "田中": [
    "1089"
  ],
  "吉田": [
    "8053"
  ],
  "渡辺": [
    "0105"
  ],
  "天谷": [
    "0470"
  ],
  "ﾑﾙｱｶ": [
    "0087"
  ]
}